README.txt
setup.py
passh/__init__.py
passh.egg-info/PKG-INFO
passh.egg-info/SOURCES.txt
passh.egg-info/dependency_links.txt
passh.egg-info/entry_points.txt
passh.egg-info/top_level.txt