Metadata-Version: 1.1
Name: passh
Version: 1.0.2
Summary: Python3 asyncio library to run SSH in parallel
Home-page: https://github.com/cybozu/passh
Author: Yamamoto, Hirotaka
Author-email: ymmt2005@gmail.com
License: MIT
Keywords: asyncio ssh
Platform: UNKNOWN
Classifier: Development Status :: 5 - Production/Stable
Classifier: Intended Audience :: Developers
Classifier: Intended Audience :: System Administrators
Classifier: License :: OSI Approved :: MIT License
Classifier: Programming Language :: Python :: 3.4
Classifier: Programming Language :: Python :: 3 :: Only
Classifier: Topic :: Software Development :: Libraries
Classifier: Topic :: System :: Networking
